{
  "path": "android.bluetooth",
  "name": "BluetoothGattDescriptor",
  "values": [
    {
      "type": "constant"
    },
    {
      "type": "constant",
      "keyword": "static",
      "identifier": "Int",
      "code": "PERMISSION_READ",
      "desc": "Descriptor read permission"
    },
    {
      "type": "constant",
      "keyword": "static",
      "identifier": "Int",
      "code": "PERMISSION_READ_ENCRYPTED",
      "desc": "Descriptor permission: Allow encrypted read operations"
    },
    {
      "type": "constant",
      "keyword": "static",
      "identifier": "Int",
      "code": "PERMISSION_READ_ENCRYPTED_MITM",
      "desc": "Descriptor permission: Allow reading with man-in-the-middle protection"
    },
    {
      "type": "constant",
      "keyword": "static",
      "identifier": "Int",
      "code": "PERMISSION_WRITE",
      "desc": "Descriptor write permission"
    },
    {
      "type": "constant",
      "keyword": "static",
      "identifier": "Int",
      "code": "PERMISSION_WRITE_ENCRYPTED",
      "desc": "Descriptor permission: Allow encrypted writes"
    },
    {
      "type": "constant",
      "keyword": "static",
      "identifier": "Int",
      "code": "PERMISSION_WRITE_ENCRYPTED_MITM",
      "desc": "Descriptor permission: Allow encrypted writes with man-in-the-middle protection"
    },
    {
      "type": "constant",
      "keyword": "static",
      "identifier": "Int",
      "code": "PERMISSION_WRITE_SIGNED",
      "desc": "Descriptor permission: Allow signed write operations"
    },
    {
      "type": "constant",
      "keyword": "static",
      "identifier": "Int",
      "code": "PERMISSION_WRITE_SIGNED_MITM",
      "desc": "Descriptor permission: Allow signed write operations with man-in-the-middle protection"
    },
    {
      "type": "ctor",
      "ctor": "<init>(uuid: UUID!, permissions: Int)\n            Create a new BluetoothGattDescriptor."
    },
    {
      "type": "method",
      "status": "public"
    },
    {
      "type": "method",
      "status": "public",
      "keyword": "open",
      "identifier": "Int",
      "code": "describeContents()",
      "desc": ""
    },
    {
      "type": "method",
      "status": "public",
      "keyword": "open",
      "identifier": "BluetoothGattCharacteristic",
      "code": "getCharacteristic()",
      "desc": "Returns the characteristic this descriptor belongs to.",
      "symbol": "!"
    },
    {
      "type": "method",
      "status": "public",
      "keyword": "open",
      "identifier": "Int",
      "code": "getPermissions()",
      "desc": "Returns the permissions for this descriptor."
    },
    {
      "type": "method",
      "status": "public",
      "keyword": "open",
      "identifier": "UUID",
      "code": "getUuid()",
      "desc": "Returns the UUID of this descriptor.",
      "symbol": "!"
    },
    {
      "type": "method",
      "status": "public",
      "keyword": "open",
      "identifier": "ByteArray",
      "code": "getValue()",
      "desc": "Returns the stored value for this descriptor",
      "symbol": "!"
    },
    {
      "type": "method",
      "status": "public",
      "keyword": "open",
      "identifier": "Boolean",
      "code": "setValue(value: ByteArray!)",
      "desc": "Updates the locally stored value of this descriptor."
    },
    {
      "type": "method",
      "status": "public",
      "keyword": "open",
      "identifier": "Unit",
      "code": "writeToParcel(out: Parcel!, flags: Int)",
      "desc": ""
    },
    {
      "type": "inherited-constants",
      "from": "Parcelable"
    },
    {
      "type": "inherited-constants",
      "from": "Int"
    },
    {
      "type": "inherited-constants",
      "from": "CONTENTS_FILE_DESCRIPTOR"
    },
    {
      "type": "inherited-constants",
      "from": "describeContents()"
    },
    {
      "type": "inherited-constants",
      "from": "Int"
    },
    {
      "type": "inherited-constants",
      "from": "PARCELABLE_WRITE_RETURN_VALUE"
    },
    {
      "type": "inherited-constants",
      "from": "writeToParcel"
    },
    {
      "type": "inherited-constants",
      "from": "Parcelable someFunction()"
    },
    {
      "type": "inherited-constants",
      "from": "void someFunction(out Parcelable)"
    },
    {
      "type": "inherited-constants",
      "from": "void someFunction(inout Parcelable)"
    }
  ]
}