{
  "path": "android.renderscript",
  "name": "FieldPacker",
  "values": [
    {
      "type": "ctor",
      "ctor": "<init>(len: Int)"
    },
    {
      "type": "ctor",
      "ctor": "<init>(data: ByteArray!)"
    },
    {
      "type": "method",
      "status": "public"
    },
    {
      "type": "method",
      "status": "public",
      "keyword": "open",
      "identifier": "Unit",
      "code": "addBoolean(v: Boolean)",
      "desc": ""
    },
    {
      "type": "method",
      "status": "public",
      "keyword": "open",
      "identifier": "Unit",
      "code": "addF32(v: Float)",
      "desc": ""
    },
    {
      "type": "method",
      "status": "public",
      "keyword": "open",
      "identifier": "Unit",
      "code": "addF32(v: Float2!)",
      "desc": ""
    },
    {
      "type": "method",
      "status": "public",
      "keyword": "open",
      "identifier": "Unit",
      "code": "addF32(v: Float3!)",
      "desc": ""
    },
    {
      "type": "method",
      "status": "public",
      "keyword": "open",
      "identifier": "Unit",
      "code": "addF32(v: Float4!)",
      "desc": ""
    },
    {
      "type": "method",
      "status": "public",
      "keyword": "open",
      "identifier": "Unit",
      "code": "addF64(v: Double)",
      "desc": ""
    },
    {
      "type": "method",
      "status": "public",
      "keyword": "open",
      "identifier": "Unit",
      "code": "addF64(v: Double2!)",
      "desc": ""
    },
    {
      "type": "method",
      "status": "public",
      "keyword": "open",
      "identifier": "Unit",
      "code": "addF64(v: Double3!)",
      "desc": ""
    },
    {
      "type": "method",
      "status": "public",
      "keyword": "open",
      "identifier": "Unit",
      "code": "addF64(v: Double4!)",
      "desc": ""
    },
    {
      "type": "method",
      "status": "public",
      "keyword": "open",
      "identifier": "Unit",
      "code": "addI16(v: Short)",
      "desc": ""
    },
    {
      "type": "method",
      "status": "public",
      "keyword": "open",
      "identifier": "Unit",
      "code": "addI16(v: Short2!)",
      "desc": ""
    },
    {
      "type": "method",
      "status": "public",
      "keyword": "open",
      "identifier": "Unit",
      "code": "addI16(v: Short3!)",
      "desc": ""
    },
    {
      "type": "method",
      "status": "public",
      "keyword": "open",
      "identifier": "Unit",
      "code": "addI16(v: Short4!)",
      "desc": ""
    },
    {
      "type": "method",
      "status": "public",
      "keyword": "open",
      "identifier": "Unit",
      "code": "addI32(v: Int)",
      "desc": ""
    },
    {
      "type": "method",
      "status": "public",
      "keyword": "open",
      "identifier": "Unit",
      "code": "addI32(v: Int2!)",
      "desc": ""
    },
    {
      "type": "method",
      "status": "public",
      "keyword": "open",
      "identifier": "Unit",
      "code": "addI32(v: Int3!)",
      "desc": ""
    },
    {
      "type": "method",
      "status": "public",
      "keyword": "open",
      "identifier": "Unit",
      "code": "addI32(v: Int4!)",
      "desc": ""
    },
    {
      "type": "method",
      "status": "public",
      "keyword": "open",
      "identifier": "Unit",
      "code": "addI64(v: Long)",
      "desc": ""
    },
    {
      "type": "method",
      "status": "public",
      "keyword": "open",
      "identifier": "Unit",
      "code": "addI64(v: Long2!)",
      "desc": ""
    },
    {
      "type": "method",
      "status": "public",
      "keyword": "open",
      "identifier": "Unit",
      "code": "addI64(v: Long3!)",
      "desc": ""
    },
    {
      "type": "method",
      "status": "public",
      "keyword": "open",
      "identifier": "Unit",
      "code": "addI64(v: Long4!)",
      "desc": ""
    },
    {
      "type": "method",
      "status": "public",
      "keyword": "open",
      "identifier": "Unit",
      "code": "addI8(v: Byte)",
      "desc": ""
    },
    {
      "type": "method",
      "status": "public",
      "keyword": "open",
      "identifier": "Unit",
      "code": "addI8(v: Byte2!)",
      "desc": ""
    },
    {
      "type": "method",
      "status": "public",
      "keyword": "open",
      "identifier": "Unit",
      "code": "addI8(v: Byte3!)",
      "desc": ""
    },
    {
      "type": "method",
      "status": "public",
      "keyword": "open",
      "identifier": "Unit",
      "code": "addI8(v: Byte4!)",
      "desc": ""
    },
    {
      "type": "method",
      "status": "public",
      "keyword": "open",
      "identifier": "Unit",
      "code": "addMatrix(v: Matrix4f!)",
      "desc": ""
    },
    {
      "type": "method",
      "status": "public",
      "keyword": "open",
      "identifier": "Unit",
      "code": "addMatrix(v: Matrix3f!)",
      "desc": ""
    },
    {
      "type": "method",
      "status": "public",
      "keyword": "open",
      "identifier": "Unit",
      "code": "addMatrix(v: Matrix2f!)",
      "desc": ""
    },
    {
      "type": "method",
      "status": "public",
      "keyword": "open",
      "identifier": "Unit",
      "code": "addObj(obj: BaseObj!)",
      "desc": ""
    },
    {
      "type": "method",
      "status": "public",
      "keyword": "open",
      "identifier": "Unit",
      "code": "addU16(v: Int)",
      "desc": ""
    },
    {
      "type": "method",
      "status": "public",
      "keyword": "open",
      "identifier": "Unit",
      "code": "addU16(v: Int2!)",
      "desc": ""
    },
    {
      "type": "method",
      "status": "public",
      "keyword": "open",
      "identifier": "Unit",
      "code": "addU16(v: Int3!)",
      "desc": ""
    },
    {
      "type": "method",
      "status": "public",
      "keyword": "open",
      "identifier": "Unit",
      "code": "addU16(v: Int4!)",
      "desc": ""
    },
    {
      "type": "method",
      "status": "public",
      "keyword": "open",
      "identifier": "Unit",
      "code": "addU32(v: Long)",
      "desc": ""
    },
    {
      "type": "method",
      "status": "public",
      "keyword": "open",
      "identifier": "Unit",
      "code": "addU32(v: Long2!)",
      "desc": ""
    },
    {
      "type": "method",
      "status": "public",
      "keyword": "open",
      "identifier": "Unit",
      "code": "addU32(v: Long3!)",
      "desc": ""
    },
    {
      "type": "method",
      "status": "public",
      "keyword": "open",
      "identifier": "Unit",
      "code": "addU32(v: Long4!)",
      "desc": ""
    },
    {
      "type": "method",
      "status": "public",
      "keyword": "open",
      "identifier": "Unit",
      "code": "addU64(v: Long)",
      "desc": ""
    },
    {
      "type": "method",
      "status": "public",
      "keyword": "open",
      "identifier": "Unit",
      "code": "addU64(v: Long2!)",
      "desc": ""
    },
    {
      "type": "method",
      "status": "public",
      "keyword": "open",
      "identifier": "Unit",
      "code": "addU64(v: Long3!)",
      "desc": ""
    },
    {
      "type": "method",
      "status": "public",
      "keyword": "open",
      "identifier": "Unit",
      "code": "addU64(v: Long4!)",
      "desc": ""
    },
    {
      "type": "method",
      "status": "public",
      "keyword": "open",
      "identifier": "Unit",
      "code": "addU8(v: Short)",
      "desc": ""
    },
    {
      "type": "method",
      "status": "public",
      "keyword": "open",
      "identifier": "Unit",
      "code": "addU8(v: Short2!)",
      "desc": ""
    },
    {
      "type": "method",
      "status": "public",
      "keyword": "open",
      "identifier": "Unit",
      "code": "addU8(v: Short3!)",
      "desc": ""
    },
    {
      "type": "method",
      "status": "public",
      "keyword": "open",
      "identifier": "Unit",
      "code": "addU8(v: Short4!)",
      "desc": ""
    },
    {
      "type": "method",
      "status": "public",
      "keyword": "open",
      "identifier": "Unit",
      "code": "align(v: Int)",
      "desc": ""
    },
    {
      "type": "method",
      "status": "public",
      "identifier": "ByteArray",
      "code": "getData()",
      "desc": "",
      "symbol": "!"
    },
    {
      "type": "method",
      "status": "public",
      "keyword": "open",
      "identifier": "Unit",
      "code": "reset()",
      "desc": ""
    },
    {
      "type": "method",
      "status": "public",
      "keyword": "open",
      "identifier": "Unit",
      "code": "reset(i: Int)",
      "desc": ""
    },
    {
      "type": "method",
      "status": "public",
      "keyword": "open",
      "identifier": "Unit",
      "code": "skip(i: Int)",
      "desc": ""
    },
    {
      "type": "method",
      "status": "public",
      "keyword": "open",
      "identifier": "Boolean",
      "code": "subBoolean()",
      "desc": ""
    },
    {
      "type": "method",
      "status": "public",
      "keyword": "open",
      "identifier": "Byte2",
      "code": "subByte2()",
      "desc": "",
      "symbol": "!"
    },
    {
      "type": "method",
      "status": "public",
      "keyword": "open",
      "identifier": "Byte3",
      "code": "subByte3()",
      "desc": "",
      "symbol": "!"
    },
    {
      "type": "method",
      "status": "public",
      "keyword": "open",
      "identifier": "Byte4",
      "code": "subByte4()",
      "desc": "",
      "symbol": "!"
    },
    {
      "type": "method",
      "status": "public",
      "keyword": "open",
      "identifier": "Double2",
      "code": "subDouble2()",
      "desc": "",
      "symbol": "!"
    },
    {
      "type": "method",
      "status": "public",
      "keyword": "open",
      "identifier": "Double3",
      "code": "subDouble3()",
      "desc": "",
      "symbol": "!"
    },
    {
      "type": "method",
      "status": "public",
      "keyword": "open",
      "identifier": "Double4",
      "code": "subDouble4()",
      "desc": "",
      "symbol": "!"
    },
    {
      "type": "method",
      "status": "public",
      "keyword": "open",
      "identifier": "Float",
      "code": "subF32()",
      "desc": ""
    },
    {
      "type": "method",
      "status": "public",
      "keyword": "open",
      "identifier": "Double",
      "code": "subF64()",
      "desc": ""
    },
    {
      "type": "method",
      "status": "public",
      "keyword": "open",
      "identifier": "Float2",
      "code": "subFloat2()",
      "desc": "",
      "symbol": "!"
    },
    {
      "type": "method",
      "status": "public",
      "keyword": "open",
      "identifier": "Float3",
      "code": "subFloat3()",
      "desc": "",
      "symbol": "!"
    },
    {
      "type": "method",
      "status": "public",
      "keyword": "open",
      "identifier": "Float4",
      "code": "subFloat4()",
      "desc": "",
      "symbol": "!"
    },
    {
      "type": "method",
      "status": "public",
      "keyword": "open",
      "identifier": "Short",
      "code": "subI16()",
      "desc": ""
    },
    {
      "type": "method",
      "status": "public",
      "keyword": "open",
      "identifier": "Int",
      "code": "subI32()",
      "desc": ""
    },
    {
      "type": "method",
      "status": "public",
      "keyword": "open",
      "identifier": "Long",
      "code": "subI64()",
      "desc": ""
    },
    {
      "type": "method",
      "status": "public",
      "keyword": "open",
      "identifier": "Byte",
      "code": "subI8()",
      "desc": ""
    },
    {
      "type": "method",
      "status": "public",
      "keyword": "open",
      "identifier": "Int2",
      "code": "subInt2()",
      "desc": "",
      "symbol": "!"
    },
    {
      "type": "method",
      "status": "public",
      "keyword": "open",
      "identifier": "Int3",
      "code": "subInt3()",
      "desc": "",
      "symbol": "!"
    },
    {
      "type": "method",
      "status": "public",
      "keyword": "open",
      "identifier": "Int4",
      "code": "subInt4()",
      "desc": "",
      "symbol": "!"
    },
    {
      "type": "method",
      "status": "public",
      "keyword": "open",
      "identifier": "Long2",
      "code": "subLong2()",
      "desc": "",
      "symbol": "!"
    },
    {
      "type": "method",
      "status": "public",
      "keyword": "open",
      "identifier": "Long3",
      "code": "subLong3()",
      "desc": "",
      "symbol": "!"
    },
    {
      "type": "method",
      "status": "public",
      "keyword": "open",
      "identifier": "Long4",
      "code": "subLong4()",
      "desc": "",
      "symbol": "!"
    },
    {
      "type": "method",
      "status": "public",
      "keyword": "open",
      "identifier": "Matrix2f",
      "code": "subMatrix2f()",
      "desc": "",
      "symbol": "!"
    },
    {
      "type": "method",
      "status": "public",
      "keyword": "open",
      "identifier": "Matrix3f",
      "code": "subMatrix3f()",
      "desc": "",
      "symbol": "!"
    },
    {
      "type": "method",
      "status": "public",
      "keyword": "open",
      "identifier": "Matrix4f",
      "code": "subMatrix4f()",
      "desc": "",
      "symbol": "!"
    },
    {
      "type": "method",
      "status": "public",
      "keyword": "open",
      "identifier": "Short2",
      "code": "subShort2()",
      "desc": "",
      "symbol": "!"
    },
    {
      "type": "method",
      "status": "public",
      "keyword": "open",
      "identifier": "Short3",
      "code": "subShort3()",
      "desc": "",
      "symbol": "!"
    },
    {
      "type": "method",
      "status": "public",
      "keyword": "open",
      "identifier": "Short4",
      "code": "subShort4()",
      "desc": "",
      "symbol": "!"
    },
    {
      "type": "method",
      "status": "public",
      "keyword": "open",
      "identifier": "Unit",
      "code": "subalign(v: Int)",
      "desc": ""
    }
  ]
}