{
  "path": "android.text",
  "name": "TextPaint",
  "values": [
    {
      "type": "ctor",
      "ctor": "<init>()"
    },
    {
      "type": "ctor",
      "ctor": "<init>(flags: Int)"
    },
    {
      "type": "ctor",
      "ctor": "<init>(p: Paint!)"
    },
    {
      "type": "method",
      "status": "public"
    },
    {
      "type": "method",
      "status": "public",
      "keyword": "open",
      "identifier": "Unit",
      "code": "set(tp: TextPaint!)",
      "desc": "Copy the fields from tp into this TextPaint, including the fields inherited from Paint."
    },
    {
      "type": "inherited-constants",
      "from": "Paint"
    },
    {
      "type": "inherited-constants",
      "from": "Int"
    },
    {
      "type": "inherited-constants",
      "from": "ANTI_ALIAS_FLAG"
    },
    {
      "type": "inherited-constants",
      "from": "Int"
    },
    {
      "type": "inherited-constants",
      "from": "CURSOR_AFTER"
    },
    {
      "type": "inherited-constants",
      "from": "Int"
    },
    {
      "type": "inherited-constants",
      "from": "CURSOR_AT"
    },
    {
      "type": "inherited-constants",
      "from": "Int"
    },
    {
      "type": "inherited-constants",
      "from": "CURSOR_AT_OR_AFTER"
    },
    {
      "type": "inherited-constants",
      "from": "Int"
    },
    {
      "type": "inherited-constants",
      "from": "CURSOR_AT_OR_BEFORE"
    },
    {
      "type": "inherited-constants",
      "from": "Int"
    },
    {
      "type": "inherited-constants",
      "from": "CURSOR_BEFORE"
    },
    {
      "type": "inherited-constants",
      "from": "Int"
    },
    {
      "type": "inherited-constants",
      "from": "DEV_KERN_TEXT_FLAG"
    },
    {
      "type": "inherited-constants",
      "from": "Int"
    },
    {
      "type": "inherited-constants",
      "from": "DITHER_FLAG"
    },
    {
      "type": "inherited-constants",
      "from": "Int"
    },
    {
      "type": "inherited-constants",
      "from": "EMBEDDED_BITMAP_TEXT_FLAG"
    },
    {
      "type": "inherited-constants",
      "from": "Int"
    },
    {
      "type": "inherited-constants",
      "from": "END_HYPHEN_EDIT_INSERT_ARMENIAN_HYPHEN"
    },
    {
      "type": "inherited-constants",
      "from": "Int"
    },
    {
      "type": "inherited-constants",
      "from": "END_HYPHEN_EDIT_INSERT_HYPHEN"
    },
    {
      "type": "inherited-constants",
      "from": "Int"
    },
    {
      "type": "inherited-constants",
      "from": "END_HYPHEN_EDIT_INSERT_MAQAF"
    },
    {
      "type": "inherited-constants",
      "from": "Int"
    },
    {
      "type": "inherited-constants",
      "from": "END_HYPHEN_EDIT_INSERT_UCAS_HYPHEN"
    },
    {
      "type": "inherited-constants",
      "from": "Int"
    },
    {
      "type": "inherited-constants",
      "from": "END_HYPHEN_EDIT_INSERT_ZWJ_AND_HYPHEN"
    },
    {
      "type": "inherited-constants",
      "from": "Int"
    },
    {
      "type": "inherited-constants",
      "from": "END_HYPHEN_EDIT_NO_EDIT"
    },
    {
      "type": "inherited-constants",
      "from": "Int"
    },
    {
      "type": "inherited-constants",
      "from": "END_HYPHEN_EDIT_REPLACE_WITH_HYPHEN"
    },
    {
      "type": "inherited-constants",
      "from": "Int"
    },
    {
      "type": "inherited-constants",
      "from": "FAKE_BOLD_TEXT_FLAG"
    },
    {
      "type": "inherited-constants",
      "from": "Typeface"
    },
    {
      "type": "inherited-constants",
      "from": "Int"
    },
    {
      "type": "inherited-constants",
      "from": "FILTER_BITMAP_FLAG"
    },
    {
      "type": "inherited-constants",
      "from": "Int"
    },
    {
      "type": "inherited-constants",
      "from": "HINTING_OFF"
    },
    {
      "type": "inherited-constants",
      "from": "Int"
    },
    {
      "type": "inherited-constants",
      "from": "HINTING_ON"
    },
    {
      "type": "inherited-constants",
      "from": "Int"
    },
    {
      "type": "inherited-constants",
      "from": "LINEAR_TEXT_FLAG"
    },
    {
      "type": "inherited-constants",
      "from": "SUBPIXEL_TEXT_FLAG"
    },
    {
      "type": "inherited-constants",
      "from": "Int"
    },
    {
      "type": "inherited-constants",
      "from": "START_HYPHEN_EDIT_INSERT_HYPHEN"
    },
    {
      "type": "inherited-constants",
      "from": "Int"
    },
    {
      "type": "inherited-constants",
      "from": "START_HYPHEN_EDIT_INSERT_ZWJ"
    },
    {
      "type": "inherited-constants",
      "from": "Int"
    },
    {
      "type": "inherited-constants",
      "from": "START_HYPHEN_EDIT_NO_EDIT"
    },
    {
      "type": "inherited-constants",
      "from": "Int"
    },
    {
      "type": "inherited-constants",
      "from": "STRIKE_THRU_TEXT_FLAG"
    },
    {
      "type": "inherited-constants",
      "from": "Int"
    },
    {
      "type": "inherited-constants",
      "from": "SUBPIXEL_TEXT_FLAG"
    },
    {
      "type": "inherited-constants",
      "from": "LINEAR_TEXT_FLAG"
    },
    {
      "type": "inherited-constants",
      "from": "Int"
    },
    {
      "type": "inherited-constants",
      "from": "UNDERLINE_TEXT_FLAG"
    },
    {
      "type": "inherited-methods",
      "from": "Paint"
    },
    {
      "type": "inherited-methods",
      "from": "Float"
    },
    {
      "type": "inherited-methods",
      "from": "ascent()"
    },
    {
      "type": "inherited-methods",
      "from": "Int"
    },
    {
      "type": "inherited-methods",
      "from": "breakText(text: CharArray!, index: Int, count: Int, maxWidth: Float, measuredWidth: FloatArray!)"
    },
    {
      "type": "inherited-methods",
      "from": "Int"
    },
    {
      "type": "inherited-methods",
      "from": "breakText(text: CharSequence!, start: Int, end: Int, measureForwards: Boolean, maxWidth: Float, measuredWidth: FloatArray!)"
    },
    {
      "type": "inherited-methods",
      "from": "Int"
    },
    {
      "type": "inherited-methods",
      "from": "breakText(text: String!, measureForwards: Boolean, maxWidth: Float, measuredWidth: FloatArray!)"
    },
    {
      "type": "inherited-methods",
      "from": "Unit"
    },
    {
      "type": "inherited-methods",
      "from": "clearShadowLayer()"
    },
    {
      "type": "inherited-methods",
      "from": "Float"
    },
    {
      "type": "inherited-methods",
      "from": "descent()"
    },
    {
      "type": "inherited-methods",
      "from": "Boolean"
    },
    {
      "type": "inherited-methods",
      "from": "equalsForTextMeasurement(other: Paint)"
    },
    {
      "type": "inherited-methods",
      "from": "Paint"
    },
    {
      "type": "inherited-methods",
      "from": "Int"
    },
    {
      "type": "inherited-methods",
      "from": "getAlpha()"
    },
    {
      "type": "inherited-methods",
      "from": "BlendMode?"
    },
    {
      "type": "inherited-methods",
      "from": "getBlendMode()"
    },
    {
      "type": "inherited-methods",
      "from": "Int"
    },
    {
      "type": "inherited-methods",
      "from": "getColor()"
    },
    {
      "type": "inherited-methods",
      "from": "ColorFilter!"
    },
    {
      "type": "inherited-methods",
      "from": "getColorFilter()"
    },
    {
      "type": "inherited-methods",
      "from": "Long"
    },
    {
      "type": "inherited-methods",
      "from": "getColorLong()"
    },
    {
      "type": "inherited-methods",
      "from": "ColorSpace"
    },
    {
      "type": "inherited-methods",
      "from": "Color"
    },
    {
      "type": "inherited-methods",
      "from": "Int"
    },
    {
      "type": "inherited-methods",
      "from": "getEndHyphenEdit()"
    },
    {
      "type": "inherited-methods",
      "from": "END_HYPHEN_EDIT_NO_EDIT"
    },
    {
      "type": "inherited-methods",
      "from": "Boolean"
    },
    {
      "type": "inherited-methods",
      "from": "getFillPath(src: Path!, dst: Path!)"
    },
    {
      "type": "inherited-methods",
      "from": "Int"
    },
    {
      "type": "inherited-methods",
      "from": "getFlags()"
    },
    {
      "type": "inherited-methods",
      "from": "String!"
    },
    {
      "type": "inherited-methods",
      "from": "getFontFeatureSettings()"
    },
    {
      "type": "inherited-methods",
      "from": "Float"
    },
    {
      "type": "inherited-methods",
      "from": "getFontMetrics(metrics: Paint.FontMetrics!)"
    },
    {
      "type": "inherited-methods",
      "from": "Paint.FontMetrics!"
    },
    {
      "type": "inherited-methods",
      "from": "getFontMetrics()"
    },
    {
      "type": "inherited-methods",
      "from": "Int"
    },
    {
      "type": "inherited-methods",
      "from": "getFontMetricsInt(fmi: Paint.FontMetricsInt!)"
    },
    {
      "type": "inherited-methods",
      "from": "Paint.FontMetricsInt!"
    },
    {
      "type": "inherited-methods",
      "from": "getFontMetricsInt()"
    },
    {
      "type": "inherited-methods",
      "from": "Float"
    },
    {
      "type": "inherited-methods",
      "from": "getFontSpacing()"
    },
    {
      "type": "inherited-methods",
      "from": "String!"
    },
    {
      "type": "inherited-methods",
      "from": "getFontVariationSettings()"
    },
    {
      "type": "inherited-methods",
      "from": "Int"
    },
    {
      "type": "inherited-methods",
      "from": "getHinting()"
    },
    {
      "type": "inherited-methods",
      "from": "HINTING_OFF"
    },
    {
      "type": "inherited-methods",
      "from": "HINTING_ON"
    },
    {
      "type": "inherited-methods",
      "from": "Float"
    },
    {
      "type": "inherited-methods",
      "from": "getLetterSpacing()"
    },
    {
      "type": "inherited-methods",
      "from": "MaskFilter!"
    },
    {
      "type": "inherited-methods",
      "from": "getMaskFilter()"
    },
    {
      "type": "inherited-methods",
      "from": "Int"
    },
    {
      "type": "inherited-methods",
      "from": "getOffsetForAdvance(text: CharArray!, start: Int, end: Int, contextStart: Int, contextEnd: Int, isRtl: Boolean, advance: Float)"
    },
    {
      "type": "inherited-methods",
      "from": "offset"
    },
    {
      "type": "inherited-methods",
      "from": "getRunAdvance"
    },
    {
      "type": "inherited-methods",
      "from": "advance"
    },
    {
      "type": "inherited-methods",
      "from": "advance"
    },
    {
      "type": "inherited-methods",
      "from": "text"
    },
    {
      "type": "inherited-methods",
      "from": "0 <= contextStart <= start <= end <= contextEnd <= text.length"
    },
    {
      "type": "inherited-methods",
      "from": "start <= result <= end"
    },
    {
      "type": "inherited-methods",
      "from": "Int"
    },
    {
      "type": "inherited-methods",
      "from": "getOffsetForAdvance(text: CharSequence!, start: Int, end: Int, contextStart: Int, contextEnd: Int, isRtl: Boolean, advance: Float)"
    },
    {
      "type": "inherited-methods",
      "from": "PathEffect!"
    },
    {
      "type": "inherited-methods",
      "from": "getPathEffect()"
    },
    {
      "type": "inherited-methods",
      "from": "Float"
    },
    {
      "type": "inherited-methods",
      "from": "getRunAdvance(text: CharArray!, start: Int, end: Int, contextStart: Int, contextEnd: Int, isRtl: Boolean, offset: Int)"
    },
    {
      "type": "inherited-methods",
      "from": "start"
    },
    {
      "type": "inherited-methods",
      "from": "end"
    },
    {
      "type": "inherited-methods",
      "from": "contextStart"
    },
    {
      "type": "inherited-methods",
      "from": "contextEnd"
    },
    {
      "type": "inherited-methods",
      "from": "contextStart..contextEnd"
    },
    {
      "type": "inherited-methods",
      "from": "start"
    },
    {
      "type": "inherited-methods",
      "from": "end"
    },
    {
      "type": "inherited-methods",
      "from": "start"
    },
    {
      "type": "inherited-methods",
      "from": "offset"
    },
    {
      "type": "inherited-methods",
      "from": "offset == end"
    },
    {
      "type": "inherited-methods",
      "from": "start"
    },
    {
      "type": "inherited-methods",
      "from": "end"
    },
    {
      "type": "inherited-methods",
      "from": "start..end"
    },
    {
      "type": "inherited-methods",
      "from": "start..contextStart"
    },
    {
      "type": "inherited-methods",
      "from": "end..contextEnd"
    },
    {
      "type": "inherited-methods",
      "from": "offset"
    },
    {
      "type": "inherited-methods",
      "from": "getOffsetForAdvance"
    },
    {
      "type": "inherited-methods",
      "from": "isRtl"
    },
    {
      "type": "inherited-methods",
      "from": "text"
    },
    {
      "type": "inherited-methods",
      "from": "0 <= contextStart <= start <= offset <= end <= contextEnd <= text.length"
    },
    {
      "type": "inherited-methods",
      "from": "Float"
    },
    {
      "type": "inherited-methods",
      "from": "getRunAdvance(text: CharSequence!, start: Int, end: Int, contextStart: Int, contextEnd: Int, isRtl: Boolean, offset: Int)"
    },
    {
      "type": "inherited-methods",
      "from": "Shader!"
    },
    {
      "type": "inherited-methods",
      "from": "getShader()"
    },
    {
      "type": "inherited-methods",
      "from": "Int"
    },
    {
      "type": "inherited-methods",
      "from": "getShadowLayerColor()"
    },
    {
      "type": "inherited-methods",
      "from": "Long"
    },
    {
      "type": "inherited-methods",
      "from": "getShadowLayerColorLong()"
    },
    {
      "type": "inherited-methods",
      "from": "Float"
    },
    {
      "type": "inherited-methods",
      "from": "getShadowLayerDx()"
    },
    {
      "type": "inherited-methods",
      "from": "Float"
    },
    {
      "type": "inherited-methods",
      "from": "getShadowLayerDy()"
    },
    {
      "type": "inherited-methods",
      "from": "Float"
    },
    {
      "type": "inherited-methods",
      "from": "getShadowLayerRadius()"
    },
    {
      "type": "inherited-methods",
      "from": "Int"
    },
    {
      "type": "inherited-methods",
      "from": "getStartHyphenEdit()"
    },
    {
      "type": "inherited-methods",
      "from": "START_HYPHEN_EDIT_NO_EDIT"
    },
    {
      "type": "inherited-methods",
      "from": "Float"
    },
    {
      "type": "inherited-methods",
      "from": "getStrikeThruPosition()"
    },
    {
      "type": "inherited-methods",
      "from": "STRIKE_THRU_TEXT_FLAG"
    },
    {
      "type": "inherited-methods",
      "from": "Float"
    },
    {
      "type": "inherited-methods",
      "from": "getStrikeThruThickness()"
    },
    {
      "type": "inherited-methods",
      "from": "Paint.Cap!"
    },
    {
      "type": "inherited-methods",
      "from": "getStrokeCap()"
    },
    {
      "type": "inherited-methods",
      "from": "Paint.Join!"
    },
    {
      "type": "inherited-methods",
      "from": "getStrokeJoin()"
    },
    {
      "type": "inherited-methods",
      "from": "Float"
    },
    {
      "type": "inherited-methods",
      "from": "getStrokeMiter()"
    },
    {
      "type": "inherited-methods",
      "from": "Float"
    },
    {
      "type": "inherited-methods",
      "from": "getStrokeWidth()"
    },
    {
      "type": "inherited-methods",
      "from": "Paint.Style!"
    },
    {
      "type": "inherited-methods",
      "from": "getStyle()"
    },
    {
      "type": "inherited-methods",
      "from": "Paint.Align!"
    },
    {
      "type": "inherited-methods",
      "from": "getTextAlign()"
    },
    {
      "type": "inherited-methods",
      "from": "Unit"
    },
    {
      "type": "inherited-methods",
      "from": "getTextBounds(text: String!, start: Int, end: Int, bounds: Rect!)"
    },
    {
      "type": "inherited-methods",
      "from": "Unit"
    },
    {
      "type": "inherited-methods",
      "from": "getTextBounds(text: CharSequence, start: Int, end: Int, bounds: Rect)"
    },
    {
      "type": "inherited-methods",
      "from": "android.text.Spanned"
    },
    {
      "type": "inherited-methods",
      "from": "android.text.StaticLayout"
    },
    {
      "type": "inherited-methods",
      "from": "android.text.Spanned"
    },
    {
      "type": "inherited-methods",
      "from": "Unit"
    },
    {
      "type": "inherited-methods",
      "from": "getTextBounds(text: CharArray!, index: Int, count: Int, bounds: Rect!)"
    },
    {
      "type": "inherited-methods",
      "from": "Locale"
    },
    {
      "type": "inherited-methods",
      "from": "getTextLocale()"
    },
    {
      "type": "inherited-methods",
      "from": "getTextLocales()"
    },
    {
      "type": "inherited-methods",
      "from": "LocaleList"
    },
    {
      "type": "inherited-methods",
      "from": "getTextLocales()"
    },
    {
      "type": "inherited-methods",
      "from": "Unit"
    },
    {
      "type": "inherited-methods",
      "from": "getTextPath(text: CharArray!, index: Int, count: Int, x: Float, y: Float, path: Path!)"
    },
    {
      "type": "inherited-methods",
      "from": "Unit"
    },
    {
      "type": "inherited-methods",
      "from": "getTextPath(text: String!, start: Int, end: Int, x: Float, y: Float, path: Path!)"
    },
    {
      "type": "inherited-methods",
      "from": "Float"
    },
    {
      "type": "inherited-methods",
      "from": "getTextRunAdvances(chars: CharArray, index: Int, count: Int, contextIndex: Int, contextCount: Int, isRtl: Boolean, advances: FloatArray?, advancesIndex: Int)"
    },
    {
      "type": "inherited-methods",
      "from": "index"
    },
    {
      "type": "inherited-methods",
      "from": "count"
    },
    {
      "type": "inherited-methods",
      "from": "advances"
    },
    {
      "type": "inherited-methods",
      "from": "Int"
    },
    {
      "type": "inherited-methods",
      "from": "getTextRunCursor(text: CharArray, contextStart: Int, contextLength: Int, isRtl: Boolean, offset: Int, cursorOpt: Int)"
    },
    {
      "type": "inherited-methods",
      "from": "CURSOR_AT"
    },
    {
      "type": "inherited-methods",
      "from": "Int"
    },
    {
      "type": "inherited-methods",
      "from": "getTextRunCursor(text: CharSequence, contextStart: Int, contextEnd: Int, isRtl: Boolean, offset: Int, cursorOpt: Int)"
    },
    {
      "type": "inherited-methods",
      "from": "CURSOR_AT"
    },
    {
      "type": "inherited-methods",
      "from": "Float"
    },
    {
      "type": "inherited-methods",
      "from": "getTextScaleX()"
    },
    {
      "type": "inherited-methods",
      "from": "Float"
    },
    {
      "type": "inherited-methods",
      "from": "getTextSize()"
    },
    {
      "type": "inherited-methods",
      "from": "Float"
    },
    {
      "type": "inherited-methods",
      "from": "getTextSkewX()"
    },
    {
      "type": "inherited-methods",
      "from": "Int"
    },
    {
      "type": "inherited-methods",
      "from": "getTextWidths(text: CharArray!, index: Int, count: Int, widths: FloatArray!)"
    },
    {
      "type": "inherited-methods",
      "from": "Int"
    },
    {
      "type": "inherited-methods",
      "from": "getTextWidths(text: CharSequence!, start: Int, end: Int, widths: FloatArray!)"
    },
    {
      "type": "inherited-methods",
      "from": "Int"
    },
    {
      "type": "inherited-methods",
      "from": "getTextWidths(text: String!, start: Int, end: Int, widths: FloatArray!)"
    },
    {
      "type": "inherited-methods",
      "from": "Int"
    },
    {
      "type": "inherited-methods",
      "from": "getTextWidths(text: String!, widths: FloatArray!)"
    },
    {
      "type": "inherited-methods",
      "from": "Typeface!"
    },
    {
      "type": "inherited-methods",
      "from": "getTypeface()"
    },
    {
      "type": "inherited-methods",
      "from": "Float"
    },
    {
      "type": "inherited-methods",
      "from": "getUnderlinePosition()"
    },
    {
      "type": "inherited-methods",
      "from": ""
    },
    {
      "type": "inherited-methods",
      "from": "Float"
    },
    {
      "type": "inherited-methods",
      "from": "getWordSpacing()"
    },
    {
      "type": "inherited-methods",
      "from": "Xfermode!"
    },
    {
      "type": "inherited-methods",
      "from": "getXfermode()"
    },
    {
      "type": "inherited-methods",
      "from": "Boolean"
    },
    {
      "type": "inherited-methods",
      "from": "hasGlyph(string: String!)"
    },
    {
      "type": "inherited-methods",
      "from": "Boolean"
    },
    {
      "type": "inherited-methods",
      "from": "isAntiAlias()"
    },
    {
      "type": "inherited-methods",
      "from": "Boolean"
    },
    {
      "type": "inherited-methods",
      "from": "isDither()"
    },
    {
      "type": "inherited-methods",
      "from": "Boolean"
    },
    {
      "type": "inherited-methods",
      "from": "isElegantTextHeight()"
    },
    {
      "type": "inherited-methods",
      "from": "Boolean"
    },
    {
      "type": "inherited-methods",
      "from": "isFakeBoldText()"
    },
    {
      "type": "inherited-methods",
      "from": "Boolean"
    },
    {
      "type": "inherited-methods",
      "from": "isFilterBitmap()"
    },
    {
      "type": "inherited-methods",
      "from": "Boolean"
    },
    {
      "type": "inherited-methods",
      "from": "isLinearText()"
    },
    {
      "type": "inherited-methods",
      "from": "Boolean"
    },
    {
      "type": "inherited-methods",
      "from": "isStrikeThruText()"
    },
    {
      "type": "inherited-methods",
      "from": "Boolean"
    },
    {
      "type": "inherited-methods",
      "from": "isSubpixelText()"
    },
    {
      "type": "inherited-methods",
      "from": "Boolean"
    },
    {
      "type": "inherited-methods",
      "from": "isUnderlineText()"
    },
    {
      "type": "inherited-methods",
      "from": "Float"
    },
    {
      "type": "inherited-methods",
      "from": "measureText(text: CharArray!, index: Int, count: Int)"
    },
    {
      "type": "inherited-methods",
      "from": "Float"
    },
    {
      "type": "inherited-methods",
      "from": "measureText(text: String!, start: Int, end: Int)"
    },
    {
      "type": "inherited-methods",
      "from": "Float"
    },
    {
      "type": "inherited-methods",
      "from": "measureText(text: String!)"
    },
    {
      "type": "inherited-methods",
      "from": "Float"
    },
    {
      "type": "inherited-methods",
      "from": "measureText(text: CharSequence!, start: Int, end: Int)"
    },
    {
      "type": "inherited-methods",
      "from": "Unit"
    },
    {
      "type": "inherited-methods",
      "from": "reset()"
    },
    {
      "type": "inherited-methods",
      "from": "Unit"
    },
    {
      "type": "inherited-methods",
      "from": "set(src: Paint!)"
    },
    {
      "type": "inherited-methods",
      "from": "Unit"
    },
    {
      "type": "inherited-methods",
      "from": "setARGB(a: Int, r: Int, g: Int, b: Int)"
    },
    {
      "type": "inherited-methods",
      "from": "Unit"
    },
    {
      "type": "inherited-methods",
      "from": "setAlpha(a: Int)"
    },
    {
      "type": "inherited-methods",
      "from": "Unit"
    },
    {
      "type": "inherited-methods",
      "from": "setAntiAlias(aa: Boolean)"
    },
    {
      "type": "inherited-methods",
      "from": "Unit"
    },
    {
      "type": "inherited-methods",
      "from": "setBlendMode(blendmode: BlendMode?)"
    },
    {
      "type": "inherited-methods",
      "from": "Unit"
    },
    {
      "type": "inherited-methods",
      "from": "setColor(color: Int)"
    },
    {
      "type": "inherited-methods",
      "from": "Unit"
    },
    {
      "type": "inherited-methods",
      "from": "setColor(color: Long)"
    },
    {
      "type": "inherited-methods",
      "from": "ColorLong"
    },
    {
      "type": "inherited-methods",
      "from": "ColorSpace"
    },
    {
      "type": "inherited-methods",
      "from": "Color"
    },
    {
      "type": "inherited-methods",
      "from": "ColorFilter!"
    },
    {
      "type": "inherited-methods",
      "from": "setColorFilter(filter: ColorFilter!)"
    },
    {
      "type": "inherited-methods",
      "from": "Unit"
    },
    {
      "type": "inherited-methods",
      "from": "setDither(dither: Boolean)"
    },
    {
      "type": "inherited-methods",
      "from": "Unit"
    },
    {
      "type": "inherited-methods",
      "from": "setElegantTextHeight(elegant: Boolean)"
    },
    {
      "type": "inherited-methods",
      "from": "Unit"
    },
    {
      "type": "inherited-methods",
      "from": "setEndHyphenEdit(endHyphen: Int)"
    },
    {
      "type": "inherited-methods",
      "from": "END_HYPHEN_EDIT_INSERT_HYPHEN"
    },
    {
      "type": "inherited-methods",
      "from": "END_HYPHEN_EDIT_NO_EDIT"
    },
    {
      "type": "inherited-methods",
      "from": "Unit"
    },
    {
      "type": "inherited-methods",
      "from": "setFakeBoldText(fakeBoldText: Boolean)"
    },
    {
      "type": "inherited-methods",
      "from": "Unit"
    },
    {
      "type": "inherited-methods",
      "from": "setFilterBitmap(filter: Boolean)"
    },
    {
      "type": "inherited-methods",
      "from": "Unit"
    },
    {
      "type": "inherited-methods",
      "from": "setFlags(flags: Int)"
    },
    {
      "type": "inherited-methods",
      "from": "Unit"
    },
    {
      "type": "inherited-methods",
      "from": "setFontFeatureSettings(settings: String!)"
    },
    {
      "type": "inherited-methods",
      "from": "Boolean"
    },
    {
      "type": "inherited-methods",
      "from": "setFontVariationSettings(fontVariationSettings: String!)"
    },
    {
      "type": "inherited-methods",
      "from": "Unit"
    },
    {
      "type": "inherited-methods",
      "from": "setHinting(mode: Int)"
    },
    {
      "type": "inherited-methods",
      "from": "HINTING_OFF"
    },
    {
      "type": "inherited-methods",
      "from": "HINTING_ON"
    },
    {
      "type": "inherited-methods",
      "from": "Unit"
    },
    {
      "type": "inherited-methods",
      "from": "setLetterSpacing(letterSpacing: Float)"
    },
    {
      "type": "inherited-methods",
      "from": "Unit"
    },
    {
      "type": "inherited-methods",
      "from": "setLinearText(linearText: Boolean)"
    },
    {
      "type": "inherited-methods",
      "from": "MaskFilter!"
    },
    {
      "type": "inherited-methods",
      "from": "setMaskFilter(maskfilter: MaskFilter!)"
    },
    {
      "type": "inherited-methods",
      "from": "PathEffect!"
    },
    {
      "type": "inherited-methods",
      "from": "setPathEffect(effect: PathEffect!)"
    },
    {
      "type": "inherited-methods",
      "from": "Shader!"
    },
    {
      "type": "inherited-methods",
      "from": "setShader(shader: Shader!)"
    },
    {
      "type": "inherited-methods",
      "from": "Unit"
    },
    {
      "type": "inherited-methods",
      "from": "setShadowLayer(radius: Float, dx: Float, dy: Float, shadowColor: Int)"
    },
    {
      "type": "inherited-methods",
      "from": "Unit"
    },
    {
      "type": "inherited-methods",
      "from": "setShadowLayer(radius: Float, dx: Float, dy: Float, shadowColor: Long)"
    },
    {
      "type": "inherited-methods",
      "from": "Unit"
    },
    {
      "type": "inherited-methods",
      "from": "setStartHyphenEdit(startHyphen: Int)"
    },
    {
      "type": "inherited-methods",
      "from": "START_HYPHEN_EDIT_INSERT_HYPHEN"
    },
    {
      "type": "inherited-methods",
      "from": "START_HYPHEN_EDIT_NO_EDIT"
    },
    {
      "type": "inherited-methods",
      "from": "Unit"
    },
    {
      "type": "inherited-methods",
      "from": "setStrikeThruText(strikeThruText: Boolean)"
    },
    {
      "type": "inherited-methods",
      "from": "Unit"
    },
    {
      "type": "inherited-methods",
      "from": "setStrokeCap(cap: Paint.Cap!)"
    },
    {
      "type": "inherited-methods",
      "from": "Unit"
    },
    {
      "type": "inherited-methods",
      "from": "setStrokeJoin(join: Paint.Join!)"
    },
    {
      "type": "inherited-methods",
      "from": "Unit"
    },
    {
      "type": "inherited-methods",
      "from": "setStrokeMiter(miter: Float)"
    },
    {
      "type": "inherited-methods",
      "from": "Unit"
    },
    {
      "type": "inherited-methods",
      "from": "setStrokeWidth(width: Float)"
    },
    {
      "type": "inherited-methods",
      "from": "Unit"
    },
    {
      "type": "inherited-methods",
      "from": "setStyle(style: Paint.Style!)"
    },
    {
      "type": "inherited-methods",
      "from": "Unit"
    },
    {
      "type": "inherited-methods",
      "from": "setSubpixelText(subpixelText: Boolean)"
    },
    {
      "type": "inherited-methods",
      "from": "Unit"
    },
    {
      "type": "inherited-methods",
      "from": "setTextAlign(align: Paint.Align!)"
    },
    {
      "type": "inherited-methods",
      "from": "Unit"
    },
    {
      "type": "inherited-methods",
      "from": "setTextLocale(locale: Locale)"
    },
    {
      "type": "inherited-methods",
      "from": "setTextLocales(android.os.LocaleList)"
    },
    {
      "type": "inherited-methods",
      "from": "Unit"
    },
    {
      "type": "inherited-methods",
      "from": "setTextLocales(locales: LocaleList)"
    },
    {
      "type": "inherited-methods",
      "from": "Locale#CHINESE"
    },
    {
      "type": "inherited-methods",
      "from": "Locale#CHINA"
    },
    {
      "type": "inherited-methods",
      "from": "Locale#JAPANESE"
    },
    {
      "type": "inherited-methods",
      "from": "Locale#JAPAN"
    },
    {
      "type": "inherited-methods",
      "from": "Unit"
    },
    {
      "type": "inherited-methods",
      "from": "setTextScaleX(scaleX: Float)"
    },
    {
      "type": "inherited-methods",
      "from": "Unit"
    },
    {
      "type": "inherited-methods",
      "from": "setTextSize(textSize: Float)"
    },
    {
      "type": "inherited-methods",
      "from": "Unit"
    },
    {
      "type": "inherited-methods",
      "from": "setTextSkewX(skewX: Float)"
    },
    {
      "type": "inherited-methods",
      "from": "Typeface!"
    },
    {
      "type": "inherited-methods",
      "from": "setTypeface(typeface: Typeface!)"
    },
    {
      "type": "inherited-methods",
      "from": "Unit"
    },
    {
      "type": "inherited-methods",
      "from": "setUnderlineText(underlineText: Boolean)"
    },
    {
      "type": "inherited-methods",
      "from": "Unit"
    },
    {
      "type": "inherited-methods",
      "from": "setWordSpacing(wordSpacing: Float)"
    },
    {
      "type": "inherited-methods",
      "from": "Xfermode!"
    },
    {
      "type": "inherited-methods",
      "from": "setXfermode(xfermode: Xfermode!)"
    },
    {
      "type": "inherited-methods",
      "from": "PorterDuffXfermode"
    }
  ]
}