{
  "path": "android.telephony.emergency",
  "name": "EmergencyNumber",
  "values": [
    {
      "type": "constant"
    },
    {
      "type": "constant",
      "keyword": "static",
      "identifier": "Int",
      "code": "EMERGENCY_CALL_ROUTING_EMERGENCY",
      "desc": "Indicates the radio or IMS implementation must handle the call through emergency routing."
    },
    {
      "type": "constant",
      "keyword": "static",
      "identifier": "Int",
      "code": "EMERGENCY_CALL_ROUTING_NORMAL",
      "desc": "Indicates the radio or IMS implementation must handle the call through normal call routing."
    },
    {
      "type": "constant",
      "keyword": "static",
      "identifier": "Int",
      "code": "EMERGENCY_CALL_ROUTING_UNKNOWN",
      "desc": "Indicated the framework does not know whether an emergency call should be placed using emergency or normal call routing."
    },
    {
      "type": "constant",
      "keyword": "static",
      "identifier": "Int",
      "code": "EMERGENCY_NUMBER_SOURCE_DATABASE",
      "desc": "Bit-field which indicates the number is from the platform-maintained database."
    },
    {
      "type": "constant",
      "keyword": "static",
      "identifier": "Int",
      "code": "EMERGENCY_NUMBER_SOURCE_DEFAULT",
      "desc": "Bit-field which indicates the number is available as default."
    },
    {
      "type": "constant",
      "keyword": "static",
      "identifier": "Int",
      "code": "EMERGENCY_NUMBER_SOURCE_MODEM_CONFIG",
      "desc": "Bit-field which indicates the number is from the modem config."
    },
    {
      "type": "constant",
      "keyword": "static",
      "identifier": "Int",
      "code": "EMERGENCY_NUMBER_SOURCE_NETWORK_SIGNALING",
      "desc": "Bit-field which indicates the number is from the network signaling."
    },
    {
      "type": "constant",
      "keyword": "static",
      "identifier": "Int",
      "code": "EMERGENCY_NUMBER_SOURCE_SIM",
      "desc": "Bit-field which indicates the number is from the sim."
    },
    {
      "type": "constant",
      "keyword": "static",
      "identifier": "Int",
      "code": "EMERGENCY_SERVICE_CATEGORY_AIEC",
      "desc": "Bit-field that indicates Emergency Service Category for Automatically Initiated eCall (AIeC) Reference: 3gpp 22."
    },
    {
      "type": "constant",
      "keyword": "static",
      "identifier": "Int",
      "code": "EMERGENCY_SERVICE_CATEGORY_AMBULANCE",
      "desc": "Bit-field that indicates Emergency Service Category for Ambulance."
    },
    {
      "type": "constant",
      "keyword": "static",
      "identifier": "Int",
      "code": "EMERGENCY_SERVICE_CATEGORY_FIRE_BRIGADE",
      "desc": "Bit-field that indicates Emergency Service Category for Fire Brigade."
    },
    {
      "type": "constant",
      "keyword": "static",
      "identifier": "Int",
      "code": "EMERGENCY_SERVICE_CATEGORY_MARINE_GUARD",
      "desc": "Bit-field that indicates Emergency Service Category for Marine Guard."
    },
    {
      "type": "constant",
      "keyword": "static",
      "identifier": "Int",
      "code": "EMERGENCY_SERVICE_CATEGORY_MIEC",
      "desc": "Bit-field that indicates Emergency Service Category for Manually Initiated eCall (MIeC) Reference: 3gpp 22."
    },
    {
      "type": "constant",
      "keyword": "static",
      "identifier": "Int",
      "code": "EMERGENCY_SERVICE_CATEGORY_MOUNTAIN_RESCUE",
      "desc": "Bit-field that indicates Emergency Service Category for Mountain Rescue."
    },
    {
      "type": "constant",
      "keyword": "static",
      "identifier": "Int",
      "code": "EMERGENCY_SERVICE_CATEGORY_POLICE",
      "desc": "Bit-field that indicates Emergency Service Category for Police."
    },
    {
      "type": "constant",
      "keyword": "static",
      "identifier": "Int",
      "code": "EMERGENCY_SERVICE_CATEGORY_UNSPECIFIED",
      "desc": "Emergency Service Category UNSPECIFIED (General emergency call, all categories) bit-field indicates that no specific services are associated with this emergency number; if the emergency number is specified, it has one or more defined emergency service categories."
    },
    {
      "type": "method",
      "status": "public"
    },
    {
      "type": "method",
      "status": "public",
      "identifier": "Int",
      "code": "compareTo(other: EmergencyNumber)",
      "desc": "Compare the display priority for this emergency number and the supplied emergency number."
    },
    {
      "type": "method",
      "status": "public",
      "identifier": "Int",
      "code": "describeContents()",
      "desc": ""
    },
    {
      "type": "method",
      "status": "public",
      "identifier": "Boolean",
      "code": "equals(other: Any?)",
      "desc": ""
    },
    {
      "type": "method",
      "status": "public",
      "identifier": "String",
      "code": "getCountryIso()",
      "desc": "Get the country code string (lowercase character) in ISO 3166 format of the emergency number."
    },
    {
      "type": "method",
      "status": "public",
      "identifier": "Int",
      "code": "getEmergencyCallRouting()",
      "desc": "Returns the emergency call routing information."
    },
    {
      "type": "method",
      "status": "public",
      "identifier": "MutableList",
      "code": "getEmergencyNumberSources()",
      "desc": "Returns a list of sources of the emergency number.",
      "symbol": "<"
    },
    {
      "type": "method",
      "status": "public",
      "identifier": "MutableList",
      "code": "getEmergencyServiceCategories()",
      "desc": "Returns the emergency service categories of the emergency number.",
      "symbol": "<"
    },
    {
      "type": "method",
      "status": "public",
      "identifier": "MutableList",
      "code": "getEmergencyUrns()",
      "desc": "Returns the list of emergency Uniform Resources Names (URN) of the emergency number.",
      "symbol": "<"
    },
    {
      "type": "method",
      "status": "public",
      "identifier": "String",
      "code": "getMnc()",
      "desc": "Get the Mobile Network Code of the emergency number."
    },
    {
      "type": "method",
      "status": "public",
      "identifier": "String",
      "code": "getNumber()",
      "desc": "Get the dialing number of the emergency number."
    },
    {
      "type": "method",
      "status": "public",
      "identifier": "Int",
      "code": "hashCode()",
      "desc": ""
    },
    {
      "type": "method",
      "status": "public",
      "identifier": "Boolean",
      "code": "isFromSources(sources: Int)",
      "desc": "Checks if the emergency number is from the specified emergency number source(s)."
    },
    {
      "type": "method",
      "status": "public",
      "identifier": "Boolean",
      "code": "isInEmergencyServiceCategories(categories: Int)",
      "desc": "Checks if the emergency number is in the supplied emergency service category(s)."
    },
    {
      "type": "method",
      "status": "public",
      "identifier": "String",
      "code": "toString()",
      "desc": ""
    },
    {
      "type": "method",
      "status": "public",
      "identifier": "Unit",
      "code": "writeToParcel(dest: Parcel!, flags: Int)",
      "desc": ""
    },
    {
      "type": "inherited-constants",
      "from": "Parcelable"
    },
    {
      "type": "inherited-constants",
      "from": "Int"
    },
    {
      "type": "inherited-constants",
      "from": "CONTENTS_FILE_DESCRIPTOR"
    },
    {
      "type": "inherited-constants",
      "from": "describeContents()"
    },
    {
      "type": "inherited-constants",
      "from": "Int"
    },
    {
      "type": "inherited-constants",
      "from": "PARCELABLE_WRITE_RETURN_VALUE"
    },
    {
      "type": "inherited-constants",
      "from": "writeToParcel"
    },
    {
      "type": "inherited-constants",
      "from": "Parcelable someFunction()"
    },
    {
      "type": "inherited-constants",
      "from": "void someFunction(out Parcelable)"
    },
    {
      "type": "inherited-constants",
      "from": "void someFunction(inout Parcelable)"
    }
  ]
}