{
  "path": "android.app.admin",
  "name": "ConnectEvent",
  "values": [
    {
      "type": "method",
      "status": "public"
    },
    {
      "type": "method",
      "status": "public",
      "identifier": "Int",
      "code": "describeContents()",
      "desc": ""
    },
    {
      "type": "method",
      "status": "public",
      "identifier": "InetAddress",
      "code": "getInetAddress()",
      "desc": "",
      "symbol": "!"
    },
    {
      "type": "method",
      "status": "public",
      "identifier": "Int",
      "code": "getPort()",
      "desc": ""
    },
    {
      "type": "method",
      "status": "public",
      "identifier": "String",
      "code": "toString()",
      "desc": ""
    },
    {
      "type": "method",
      "status": "public",
      "identifier": "Unit",
      "code": "writeToParcel(out: Parcel!, flags: Int)",
      "desc": ""
    },
    {
      "type": "inherited-constants",
      "from": "Parcelable"
    },
    {
      "type": "inherited-constants",
      "from": "Int"
    },
    {
      "type": "inherited-constants",
      "from": "CONTENTS_FILE_DESCRIPTOR"
    },
    {
      "type": "inherited-constants",
      "from": "describeContents()"
    },
    {
      "type": "inherited-constants",
      "from": "Int"
    },
    {
      "type": "inherited-constants",
      "from": "PARCELABLE_WRITE_RETURN_VALUE"
    },
    {
      "type": "inherited-constants",
      "from": "writeToParcel"
    },
    {
      "type": "inherited-constants",
      "from": "Parcelable someFunction()"
    },
    {
      "type": "inherited-constants",
      "from": "void someFunction(out Parcelable)"
    },
    {
      "type": "inherited-constants",
      "from": "void someFunction(inout Parcelable)"
    },
    {
      "type": "inherited-methods",
      "from": "NetworkEvent"
    },
    {
      "type": "inherited-methods",
      "from": "Long"
    },
    {
      "type": "inherited-methods",
      "from": "getId()"
    },
    {
      "type": "inherited-methods",
      "from": "String!"
    },
    {
      "type": "inherited-methods",
      "from": "getPackageName()"
    },
    {
      "type": "inherited-methods",
      "from": "PackageManager#getNameForUid"
    },
    {
      "type": "inherited-methods",
      "from": "Long"
    },
    {
      "type": "inherited-methods",
      "from": "getTimestamp()"
    }
  ]
}