{
  "path": "java.lang",
  "name": "BootstrapMethodError",
  "values": [
    {
      "type": "ctor",
      "ctor": "<init>()\n            Constructs a BootstrapMethodError with no detail message."
    },
    {
      "type": "ctor",
      "ctor": "<init>(s: String!)\n            Constructs a BootstrapMethodError with the specified detail message."
    },
    {
      "type": "ctor",
      "ctor": "<init>(s: String!, cause: Throwable!)\n            Constructs a BootstrapMethodError with the specified detail message and cause."
    },
    {
      "type": "ctor",
      "ctor": "<init>(cause: Throwable!)\n            Constructs a BootstrapMethodError with the specified cause."
    }
  ]
}