{
  "path": "java.time",
  "name": "Clock",
  "values": [
    {
      "type": "method",
      "status": "public"
    },
    {
      "type": "method",
      "status": "public",
      "keyword": "open",
      "identifier": "Boolean",
      "code": "equals(other: Any?)",
      "desc": "Checks if this clock is equal to another clock."
    },
    {
      "type": "method",
      "status": "public",
      "keyword": "open",
      "identifier": "Clock",
      "code": "fixed(fixedInstant: Instant!, zone: ZoneId!)",
      "desc": "Obtains a clock that always returns the same instant.",
      "symbol": "!"
    },
    {
      "type": "method",
      "status": "public",
      "keyword": "abstract",
      "identifier": "ZoneId",
      "code": "getZone()",
      "desc": "Gets the time-zone being used to create dates and times.",
      "symbol": "!"
    },
    {
      "type": "method",
      "status": "public",
      "keyword": "open",
      "identifier": "Int",
      "code": "hashCode()",
      "desc": "A hash code for this clock."
    },
    {
      "type": "method",
      "status": "public",
      "keyword": "abstract",
      "identifier": "Instant",
      "code": "instant()",
      "desc": "Gets the current instant of the clock.",
      "symbol": "!"
    },
    {
      "type": "method",
      "status": "public",
      "keyword": "open",
      "identifier": "Long",
      "code": "millis()",
      "desc": "Gets the current millisecond instant of the clock."
    },
    {
      "type": "method",
      "status": "public",
      "keyword": "open",
      "identifier": "Clock",
      "code": "offset(baseClock: Clock!, offsetDuration: Duration!)",
      "desc": "Obtains a clock that returns instants from the specified clock with the specified duration added",
      "symbol": "!"
    },
    {
      "type": "method",
      "status": "public",
      "keyword": "open",
      "identifier": "Clock",
      "code": "system(zone: ZoneId!)",
      "desc": "Obtains a clock that returns the current instant using best available system clock.",
      "symbol": "!"
    },
    {
      "type": "method",
      "status": "public",
      "keyword": "open",
      "identifier": "Clock",
      "code": "systemDefaultZone()",
      "desc": "Obtains a clock that returns the current instant using the best available system clock, converting to date and time using the default time-zone.",
      "symbol": "!"
    },
    {
      "type": "method",
      "status": "public",
      "keyword": "open",
      "identifier": "Clock",
      "code": "systemUTC()",
      "desc": "Obtains a clock that returns the current instant using the best available system clock, converting to date and time using the UTC time-zone.",
      "symbol": "!"
    },
    {
      "type": "method",
      "status": "public",
      "keyword": "open",
      "identifier": "Clock",
      "code": "tick(baseClock: Clock!, tickDuration: Duration!)",
      "desc": "Obtains a clock that returns instants from the specified clock truncated to the nearest occurrence of the specified duration.",
      "symbol": "!"
    },
    {
      "type": "method",
      "status": "public",
      "keyword": "open",
      "identifier": "Clock",
      "code": "tickMinutes(zone: ZoneId!)",
      "desc": "Obtains a clock that returns the current instant ticking in whole minutes using best available system clock.",
      "symbol": "!"
    },
    {
      "type": "method",
      "status": "public",
      "keyword": "open",
      "identifier": "Clock",
      "code": "tickSeconds(zone: ZoneId!)",
      "desc": "Obtains a clock that returns the current instant ticking in whole seconds using best available system clock.",
      "symbol": "!"
    },
    {
      "type": "method",
      "status": "public",
      "keyword": "abstract",
      "identifier": "Clock",
      "code": "withZone(zone: ZoneId!)",
      "desc": "Returns a copy of this clock with a different time-zone.",
      "symbol": "!"
    }
  ]
}