{
  "path": "java.util.stream",
  "name": "StreamSupport",
  "values": [
    {
      "type": "method",
      "status": "public"
    },
    {
      "type": "method",
      "status": "public",
      "keyword": "static",
      "identifier": "DoubleStream",
      "code": "doubleStream(spliterator: Spliterator.OfDouble!, parallel: Boolean)",
      "desc": "Creates a new sequential or parallel DoubleStream from a Spliterator.OfDouble.",
      "symbol": "!"
    },
    {
      "type": "method",
      "status": "public",
      "keyword": "static",
      "identifier": "DoubleStream",
      "code": "doubleStream(supplier: Supplier<out Spliterator.OfDouble!>!, characteristics: Int, parallel: Boolean)",
      "desc": "Creates a new sequential or parallel DoubleStream from a Supplier of Spliterator.OfDouble.",
      "symbol": "!"
    },
    {
      "type": "method",
      "status": "public",
      "keyword": "static",
      "identifier": "IntStream",
      "code": "intStream(spliterator: Spliterator.OfInt!, parallel: Boolean)",
      "desc": "Creates a new sequential or parallel IntStream from a Spliterator.OfInt.",
      "symbol": "!"
    },
    {
      "type": "method",
      "status": "public",
      "keyword": "static",
      "identifier": "IntStream",
      "code": "intStream(supplier: Supplier<out Spliterator.OfInt!>!, characteristics: Int, parallel: Boolean)",
      "desc": "Creates a new sequential or parallel IntStream from a Supplier of Spliterator.OfInt.",
      "symbol": "!"
    },
    {
      "type": "method",
      "status": "public",
      "keyword": "static",
      "identifier": "LongStream",
      "code": "longStream(spliterator: Spliterator.OfLong!, parallel: Boolean)",
      "desc": "Creates a new sequential or parallel LongStream from a Spliterator.OfLong.",
      "symbol": "!"
    },
    {
      "type": "method",
      "status": "public",
      "keyword": "static",
      "identifier": "LongStream",
      "code": "longStream(supplier: Supplier<out Spliterator.OfLong!>!, characteristics: Int, parallel: Boolean)",
      "desc": "Creates a new sequential or parallel LongStream from a Supplier of Spliterator.OfLong.",
      "symbol": "!"
    },
    {
      "type": "method",
      "status": "public",
      "keyword": "static",
      "identifier": "Stream",
      "code": "stream(spliterator: Spliterator<T>!, parallel: Boolean)",
      "desc": "Creates a new sequential or parallel Stream from a Spliterator.",
      "symbol": "<"
    },
    {
      "type": "method",
      "status": "public",
      "keyword": "static",
      "identifier": "Stream",
      "code": "stream(supplier: Supplier<out Spliterator<T>!>!, characteristics: Int, parallel: Boolean)",
      "desc": "Creates a new sequential or parallel Stream from a Supplier of Spliterator.",
      "symbol": "<"
    }
  ]
}