{
  "path": "java.security",
  "name": "KeyRep",
  "values": [
    {
      "type": "ctor",
      "ctor": "<init>(type: KeyRep.Type!, algorithm: String!, format: String!, encoded: ByteArray!)\n            Construct the alternate Key class."
    },
    {
      "type": "method",
      "status": "protected"
    },
    {
      "type": "method",
      "status": "protected",
      "keyword": "open",
      "identifier": "Any",
      "code": "readResolve()",
      "desc": "Resolve the Key object.",
      "symbol": "!"
    },
    {
      "type": "nested-classes"
    },
    {
      "type": "nested-classes",
      "code": "Type",
      "desc": "Key type."
    }
  ]
}